nonebot_plugin_bf5_grouptools/__init__.py
nonebot_plugin_bf5_grouptools/data.py
nonebot_plugin_bf5_grouptools/network.py
nonebot_plugin_bf5_grouptools/utils.py
nonebot_plugin_bf5_grouptools-2.0.2.dist-info/METADATA
nonebot_plugin_bf5_grouptools-2.0.2.dist-info/WHEEL
nonebot_plugin_bf5_grouptools-2.0.2.dist-info/RECORD
