Metadata-Version: 2.1
Name: nonebot_plugin_bf5_grouptools
Version: 2.0.2
Summary: 基于 Nonebot2 的战地 5 QQ 群管理插件。
Home-page: https://github.com/Lonely-Sails/nonebot-plugin-BF5-grouptools
License: GPL3
Keywords: nonebot,nonebot2,BF5,onebot
Author: Lonely-Sails
Requires-Python: >=3.8,<4.0
Classifier: License :: Other/Proprietary License
Classifier: Programming Language :: Python :: 3
Classifier: Programming Language :: Python :: 3.8
Classifier: Programming Language :: Python :: 3.9
Classifier: Programming Language :: Python :: 3.10
Classifier: Programming Language :: Python :: 3.11
Classifier: Programming Language :: Python :: 3.12
Requires-Dist: httpx (>=0.27.0,<0.28.0)
Requires-Dist: nonebot-adapter-onebot (>=2.4.3,<3.0.0)
Requires-Dist: nonebot-plugin-localstore (>=0.7.0,<0.8.0)
Requires-Dist: nonebot2 (>=2.2.0,<3.0.0)
Project-URL: Documentation, https://github.com/Lonely-Sails/nonebot-plugin-BF5-grouptools#readme
Project-URL: Repository, https://github.com/Lonely-Sails/nonebot-plugin-BF5-grouptools
